{"cameraMode":{"drawMode":0,"name":"Shaded","section":"Shading Mode"},"sceneLighting":true,"audioPlay":false,"sceneViewState":{"showFog":true,"showMaterialUpdate":false,"showSkybox":true,"showFlares":true,"showImageEffects":true,"showParticleSystems":true},"in2DMode":false,"pivot":{"x":-2.453218698501587,"y":2.3898332118988039,"z":-0.9214203357696533},"rotation":{"x":-0.06624570488929749,"y":0.02753477357327938,"z":-0.0018278489587828518,"w":-0.9974217414855957},"size":1.7147303819656373,"orthographic":false}